[
  {
    "Id": 1,
    "UserId": 1,
    "TestId": 1,
    "Score": 100,
    "CorrectAnswers": 1,
    "TotalQuestions": 1,
    "TimeSpentSeconds": 0,
    "CompletedAt": "2026-03-05T00:06:29.7230712+03:00",
    "Status": "completed",
    "ResultTitle": null
  },
  {
    "Id": 2,
    "UserId": 1,
    "TestId": 1,
    "Score": 100,
    "CorrectAnswers": 1,
    "TotalQuestions": 1,
    "TimeSpentSeconds": 0,
    "CompletedAt": "2026-03-05T00:18:01.9657843+03:00",
    "Status": "completed",
    "ResultTitle": null
  },
  {
    "Id": 3,
    "UserId": 1,
    "TestId": 1,
    "Score": 100,
    "CorrectAnswers": 3,
    "TotalQuestions": 3,
    "TimeSpentSeconds": 0,
    "CompletedAt": "2026-03-05T00:48:42.5647183+03:00",
    "Status": "completed",
    "ResultTitle": null
  },
  {
    "Id": 4,
    "UserId": 1,
    "TestId": 1,
    "Score": 100,
    "CorrectAnswers": 3,
    "TotalQuestions": 3,
    "TimeSpentSeconds": 0,
    "CompletedAt": "2026-03-28T20:21:05.0222367+03:00",
    "Status": "completed",
    "ResultTitle": null
  },
  {
    "Id": 5,
    "UserId": 1,
    "TestId": 3,
    "Score": 100,
    "CorrectAnswers": 3,
    "TotalQuestions": 3,
    "TimeSpentSeconds": 0,
    "CompletedAt": "2026-03-28T21:36:54.7969137+03:00",
    "Status": "completed",
    "ResultTitle": null
  },
  {
    "Id": 6,
    "UserId": 1,
    "TestId": 1,
    "Score": 100,
    "CorrectAnswers": 3,
    "TotalQuestions": 3,
    "TimeSpentSeconds": 0,
    "CompletedAt": "2026-03-28T21:49:49.9981594+03:00",
    "Status": "completed",
    "ResultTitle": null
  },
  {
    "Id": 7,
    "UserId": 1,
    "TestId": 3,
    "Score": 100,
    "CorrectAnswers": 3,
    "TotalQuestions": 3,
    "TimeSpentSeconds": 0,
    "CompletedAt": "2026-03-28T21:50:40.0671553+03:00",
    "Status": "completed",
    "ResultTitle": null
  },
  {
    "Id": 8,
    "UserId": 1,
    "TestId": 1,
    "Score": 100,
    "CorrectAnswers": 3,
    "TotalQuestions": 3,
    "TimeSpentSeconds": 0,
    "CompletedAt": "2026-03-28T21:56:07.9891718+03:00",
    "Status": "completed",
    "ResultTitle": null
  },
  {
    "Id": 9,
    "UserId": 1,
    "TestId": 3,
    "Score": 100,
    "CorrectAnswers": 3,
    "TotalQuestions": 3,
    "TimeSpentSeconds": 0,
    "CompletedAt": "2026-03-28T21:56:31.5144639+03:00",
    "Status": "completed",
    "ResultTitle": null
  },
  {
    "Id": 10,
    "UserId": 1,
    "TestId": 4,
    "Score": 100,
    "CorrectAnswers": 3,
    "TotalQuestions": 3,
    "TimeSpentSeconds": 0,
    "CompletedAt": "2026-03-28T22:00:33.9731054+03:00",
    "Status": "completed",
    "ResultTitle": null
  },
  {
    "Id": 11,
    "UserId": 1,
    "TestId": 4,
    "Score": 3,
    "CorrectAnswers": 2,
    "TotalQuestions": 3,
    "TimeSpentSeconds": 2,
    "CompletedAt": "2026-03-28T22:09:41.1231731+03:00",
    "Status": "completed",
    "ResultTitle": null
  },
  {
    "Id": 12,
    "UserId": 1,
    "TestId": 1,
    "Score": 0,
    "CorrectAnswers": 2,
    "TotalQuestions": 3,
    "TimeSpentSeconds": 2,
    "CompletedAt": "2026-03-28T22:13:48.3302847+03:00",
    "Status": "completed",
    "ResultTitle": null
  },
  {
    "Id": 13,
    "UserId": 1,
    "TestId": 4,
    "Score": 5,
    "CorrectAnswers": 2,
    "TotalQuestions": 3,
    "TimeSpentSeconds": 5,
    "CompletedAt": "2026-03-28T22:14:14.4862089+03:00",
    "Status": "completed",
    "ResultTitle": null
  },
  {
    "Id": 14,
    "UserId": 1,
    "TestId": 4,
    "Score": 2,
    "CorrectAnswers": 2,
    "TotalQuestions": 3,
    "TimeSpentSeconds": 2,
    "CompletedAt": "2026-03-28T22:15:37.2150628+03:00",
    "Status": "completed",
    "ResultTitle": null
  },
  {
    "Id": 15,
    "UserId": 1,
    "TestId": 4,
    "Score": 6,
    "CorrectAnswers": 2,
    "TotalQuestions": 3,
    "TimeSpentSeconds": 3,
    "CompletedAt": "2026-03-28T22:27:22.3419516+03:00",
    "Status": "completed",
    "ResultTitle": null
  },
  {
    "Id": 16,
    "UserId": 1,
    "TestId": 1,
    "Score": 0,
    "CorrectAnswers": 2,
    "TotalQuestions": 3,
    "TimeSpentSeconds": 2,
    "CompletedAt": "2026-03-28T22:28:21.2165939+03:00",
    "Status": "completed",
    "ResultTitle": null
  },
  {
    "Id": 17,
    "UserId": 1,
    "TestId": 1,
    "Score": 0,
    "CorrectAnswers": 2,
    "TotalQuestions": 3,
    "TimeSpentSeconds": 4,
    "CompletedAt": "2026-03-28T23:05:29.0063138+03:00",
    "Status": "completed",
    "ResultTitle": null
  },
  {
    "Id": 18,
    "UserId": 1,
    "TestId": 4,
    "Score": 4,
    "CorrectAnswers": 2,
    "TotalQuestions": 3,
    "TimeSpentSeconds": 4,
    "CompletedAt": "2026-03-29T11:38:16.3385718+03:00",
    "Status": "completed",
    "ResultTitle": null
  },
  {
    "Id": 19,
    "UserId": 1,
    "TestId": 1,
    "Score": 0,
    "CorrectAnswers": 2,
    "TotalQuestions": 3,
    "TimeSpentSeconds": 8,
    "CompletedAt": "2026-03-30T10:43:00.5798559+03:00",
    "Status": "completed",
    "ResultTitle": null
  },
  {
    "Id": 20,
    "UserId": 1,
    "TestId": 1,
    "Score": 0,
    "CorrectAnswers": 2,
    "TotalQuestions": 3,
    "TimeSpentSeconds": 8,
    "CompletedAt": "2026-03-30T10:43:31.9503776+03:00",
    "Status": "completed",
    "ResultTitle": null
  },
  {
    "Id": 21,
    "UserId": 1,
    "TestId": 4,
    "Score": 4,
    "CorrectAnswers": 2,
    "TotalQuestions": 3,
    "TimeSpentSeconds": 5,
    "CompletedAt": "2026-03-30T10:44:03.9376918+03:00",
    "Status": "completed",
    "ResultTitle": null
  },
  {
    "Id": 22,
    "UserId": 1,
    "TestId": 4,
    "Score": 3,
    "CorrectAnswers": 2,
    "TotalQuestions": 3,
    "TimeSpentSeconds": 37,
    "CompletedAt": "2026-03-30T10:50:32.108125+03:00",
    "Status": "completed",
    "ResultTitle": null
  }
]